freetype-stubs/__init__.pyi
freetype-stubs/ft_errors.pyi
freetype-stubs/ft_structs.pyi
freetype-stubs/ft_types.pyi
freetype-stubs/raw.pyi
freetype-stubs/ft_enums/__init__.pyi
freetype-stubs/ft_enums/ft_color_root_transform.pyi
freetype-stubs/ft_enums/ft_curve_tags.pyi
freetype-stubs/ft_enums/ft_encodings.pyi
freetype-stubs/ft_enums/ft_face_flags.pyi
freetype-stubs/ft_enums/ft_fstypes.pyi
freetype-stubs/ft_enums/ft_glyph_bbox_modes.pyi
freetype-stubs/ft_enums/ft_glyph_formats.pyi
freetype-stubs/ft_enums/ft_kerning_modes.pyi
freetype-stubs/ft_enums/ft_lcd_filters.pyi
freetype-stubs/ft_enums/ft_load_flags.pyi
freetype-stubs/ft_enums/ft_load_targets.pyi
freetype-stubs/ft_enums/ft_open_modes.pyi
freetype-stubs/ft_enums/ft_outline_flags.pyi
freetype-stubs/ft_enums/ft_pixel_modes.pyi
freetype-stubs/ft_enums/ft_render_modes.pyi
freetype-stubs/ft_enums/ft_stroker_borders.pyi
freetype-stubs/ft_enums/ft_stroker_linecaps.pyi
freetype-stubs/ft_enums/ft_stroker_linejoins.pyi
freetype-stubs/ft_enums/ft_style_flags.pyi
freetype-stubs/ft_enums/tt_adobe_ids.pyi
freetype-stubs/ft_enums/tt_apple_ids.pyi
freetype-stubs/ft_enums/tt_mac_ids.pyi
freetype-stubs/ft_enums/tt_mac_langids.pyi
freetype-stubs/ft_enums/tt_ms_ids.pyi
freetype-stubs/ft_enums/tt_ms_langids.pyi
freetype-stubs/ft_enums/tt_name_ids.pyi
freetype-stubs/ft_enums/tt_platforms.pyi
freetype_py_stubs-2.5.1.dist-info/LICENSE
freetype_py_stubs-2.5.1.dist-info/METADATA
freetype_py_stubs-2.5.1.dist-info/WHEEL
freetype_py_stubs-2.5.1.dist-info/top_level.txt
freetype_py_stubs-2.5.1.dist-info/RECORD
