Metadata-Version: 2.1
Name: freetype-py-stubs
Version: 2.5.1
Summary: Stubs for freetype-py.
Author-email: HivertMoZara <worldmozara@163.com>
License: MIT
Project-URL: Homepage, https://github.com/NCBM/freetype-py-stubs
Project-URL: Repository, https://github.com/NCBM/freetype-py-stubs
Requires-Python: >=3.7
License-File: LICENSE
Requires-Dist: freetype-py <3,>=2.5.1
Requires-Dist: typing-extensions <5,>=4.6.0
